{
  "sections": {
    "6dffa976-689c-49d8-b996-0a573041ba4c": {
      "type": "image-with-text-2",
      "blocks": {
        "template--16875088249132__6dffa976-689c-49d8-b996-0a573041ba4c-16680265120462c645-0": {
          "type": "heading",
          "settings": {
            "heading": "<p>Sustainablemethods<\/p>",
            "heading_size": "h1",
            "heading_style": "2"
          }
        },
        "template--16875088249132__6dffa976-689c-49d8-b996-0a573041ba4c-16680265120462c645-1": {
          "type": "text",
          "settings": {
            "text": "<p>Our sustainable supply chain methods cast synthetic gemstones in a new light. As a great sustainable alternative to mined stones, they exhibit the exact same optical properties as their natural counterparts, without unethical and irresponsible roots. We combine age-old craftsmanship with modern-day standards to design diamond stimulants that stand the test of time.<\/p>",
            "text_style": "body"
          }
        }
      },
      "block_order": [
        "template--16875088249132__6dffa976-689c-49d8-b996-0a573041ba4c-16680265120462c645-0",
        "template--16875088249132__6dffa976-689c-49d8-b996-0a573041ba4c-16680265120462c645-1"
      ],
      "settings": {
        "image": "shopify:\/\/shop_images\/ie-banner-10.png",
        "height": "adapt",
        "desktop_image_width": "medium",
        "layout": "image_first",
        "desktop_content_position": "top",
        "desktop_content_alignment": "left",
        "content_layout": "no-overlap",
        "color_scheme": "background-1",
        "full_width": false,
        "no_page_padding": true,
        "mobile_content_alignment": "left",
        "padding_top": 0,
        "padding_bottom": 0
      }
    },
    "39e64e18-3f0e-4873-8098-f5fd22dcb8f0": {
      "type": "rich-text-2",
      "blocks": {
        "template--16689943773466__39e64e18-3f0e-4873-8098-f5fd22dcb8f0-1666336147034b9027-1": {
          "type": "text",
          "settings": {
            "text": "<p><em>We only have one Earth. And we believe everyone on it is precious.<br\/>We create jewelry to be a permanent part of our lives for generations, all the while challenging ourselves to keep improving our teams, our suppliers, our customers, the communities, and the environment we operate within.<\/em><\/p>"
          }
        },
        "23b5ae95-e6b4-438b-a258-329b86868079": {
          "type": "caption",
          "settings": {
            "caption": "- INFINITE ELEMENTS -",
            "text_style": "caption-with-letter-spacing",
            "text_size": "large"
          }
        }
      },
      "block_order": [
        "template--16689943773466__39e64e18-3f0e-4873-8098-f5fd22dcb8f0-1666336147034b9027-1",
        "23b5ae95-e6b4-438b-a258-329b86868079"
      ],
      "settings": {
        "desktop_content_position": "center",
        "content_alignment": "center",
        "color_scheme": "background-2",
        "full_width": true,
        "padding_top": 92,
        "padding_bottom": 92
      }
    },
    "656efc8c-cfb3-402b-9bbf-b34e30b9c339": {
      "type": "image-with-text-2",
      "blocks": {
        "template--16875088249132__656efc8c-cfb3-402b-9bbf-b34e30b9c339-1668027265ff5a6012-0": {
          "type": "heading",
          "settings": {
            "heading": "<p>Ethical and Responsible<\/p>",
            "heading_size": "h2",
            "heading_style": "2"
          }
        },
        "template--16875088249132__656efc8c-cfb3-402b-9bbf-b34e30b9c339-1668027265ff5a6012-1": {
          "type": "text",
          "settings": {
            "text": "<p>We ensure ethical and responsible sourcing practices of our raw materials as well as fair wages and safe working conditions for our craftsmen and factory<\/p>",
            "text_style": "body"
          }
        }
      },
      "block_order": [
        "template--16875088249132__656efc8c-cfb3-402b-9bbf-b34e30b9c339-1668027265ff5a6012-0",
        "template--16875088249132__656efc8c-cfb3-402b-9bbf-b34e30b9c339-1668027265ff5a6012-1"
      ],
      "settings": {
        "image": "shopify:\/\/shop_images\/ie-banner-11.jpg",
        "height": "small",
        "desktop_image_width": "medium",
        "layout": "text_first",
        "desktop_content_position": "top",
        "desktop_content_alignment": "left",
        "content_layout": "no-overlap",
        "color_scheme": "background-2",
        "full_width": false,
        "no_page_padding": false,
        "mobile_content_alignment": "left",
        "padding_top": 60,
        "padding_bottom": 0
      }
    },
    "81eb2a91-1801-4318-be24-c82ece53ce1f": {
      "type": "image-with-text-2",
      "blocks": {
        "template--16875088249132__81eb2a91-1801-4318-be24-c82ece53ce1f-16680275231732ab4a-0": {
          "type": "heading",
          "settings": {
            "heading": "<p>Vertically Integrated<\/p>",
            "heading_size": "h2",
            "heading_style": "2"
          }
        },
        "template--16875088249132__81eb2a91-1801-4318-be24-c82ece53ce1f-16680275231732ab4a-1": {
          "type": "text",
          "settings": {
            "text": "<p>Pioneering a vertically integrated solution to the mastery of cubic zirconia means producing the highest quality stones to the highest standard of transparency.<\/p>",
            "text_style": "body"
          }
        }
      },
      "block_order": [
        "template--16875088249132__81eb2a91-1801-4318-be24-c82ece53ce1f-16680275231732ab4a-0",
        "template--16875088249132__81eb2a91-1801-4318-be24-c82ece53ce1f-16680275231732ab4a-1"
      ],
      "settings": {
        "image": "shopify:\/\/shop_images\/ie-banner-12.png",
        "height": "adapt",
        "desktop_image_width": "medium",
        "layout": "image_first",
        "desktop_content_position": "top",
        "desktop_content_alignment": "center",
        "content_layout": "no-overlap",
        "color_scheme": "background-2",
        "full_width": false,
        "no_page_padding": false,
        "mobile_content_alignment": "left",
        "padding_top": 0,
        "padding_bottom": 0
      }
    },
    "2cbf3fba-0910-4e30-962e-98412206bb40": {
      "type": "image-with-text-2",
      "blocks": {
        "template--16875088249132__2cbf3fba-0910-4e30-962e-98412206bb40-1668027759499224b9-0": {
          "type": "heading",
          "settings": {
            "heading": "<p>Quality Control<\/p>",
            "heading_size": "h2",
            "heading_style": "2"
          }
        },
        "template--16875088249132__2cbf3fba-0910-4e30-962e-98412206bb40-1668027759499224b9-1": {
          "type": "text",
          "settings": {
            "text": "<p>Our strict quality control processes guarantee that we meet the highest requirements for the best quality, so that your stone lasts forever.<\/p>",
            "text_style": "body"
          }
        }
      },
      "block_order": [
        "template--16875088249132__2cbf3fba-0910-4e30-962e-98412206bb40-1668027759499224b9-0",
        "template--16875088249132__2cbf3fba-0910-4e30-962e-98412206bb40-1668027759499224b9-1"
      ],
      "settings": {
        "image": "shopify:\/\/shop_images\/ie-banner-13.png",
        "height": "small",
        "desktop_image_width": "medium",
        "layout": "text_first",
        "desktop_content_position": "top",
        "desktop_content_alignment": "center",
        "content_layout": "no-overlap",
        "color_scheme": "background-2",
        "full_width": false,
        "no_page_padding": false,
        "mobile_content_alignment": "left",
        "padding_top": 0,
        "padding_bottom": 60
      }
    },
    "9da261a0-b1c5-4353-be50-dbd2ab52b02b": {
      "type": "rich-text-2",
      "blocks": {
        "template--16875088249132__9da261a0-b1c5-4353-be50-dbd2ab52b02b-1668028179046a3fe4-0": {
          "type": "heading",
          "settings": {
            "heading": "<p>Differentiators<\/p>",
            "heading_size": "h1",
            "heading_style": "2"
          }
        }
      },
      "block_order": [
        "template--16875088249132__9da261a0-b1c5-4353-be50-dbd2ab52b02b-1668028179046a3fe4-0"
      ],
      "settings": {
        "desktop_content_position": "center",
        "content_alignment": "center",
        "color_scheme": "background-1",
        "full_width": true,
        "padding_top": 80,
        "padding_bottom": 80
      }
    },
    "900b0644-ef3b-4434-a2e4-746f1dada1bb": {
      "type": "multicolumn-2",
      "blocks": {
        "template--16875088249132__900b0644-ef3b-4434-a2e4-746f1dada1bb-16680282293c3ed090-0": {
          "type": "column",
          "settings": {
            "image": "shopify:\/\/shop_images\/ie-banner-14.jpg",
            "title": "CREATIVITY",
            "title_size": "h4",
            "title_style": "default",
            "text": "<p>From inspiration brief to collection launch, Infinite Elements’s creative process is unique prolific. With a focus on trend curation, design, and meaningful branding, every piece tells a story and embodies over 30 years of mastered craftmanship. The continuous evolution of material and technique makes Infinite Elements the leader of crystal cut creations.<\/p>",
            "link_label": "",
            "link": "",
            "icon": "",
            "icon_size": 18
          }
        },
        "template--16875088249132__900b0644-ef3b-4434-a2e4-746f1dada1bb-16680282293c3ed090-1": {
          "type": "column",
          "settings": {
            "image": "shopify:\/\/shop_images\/ie-banner-15.jpg",
            "title": "KNOW-HOW",
            "title_size": "h4",
            "title_style": "default",
            "text": "<p>New cuts, shades, and sizes are conceived and realized every day in the historical Wattens headquarters, pushing the boundaries of crystal. Infinite Elements’s know-how not only focuses on refining the crystal, it also explores methods that make the most incredible pieces possible. Beading, bezel and prong settings are some of the techniques used to enhance the sparke and create exquisite refinement.<\/p>",
            "link_label": "",
            "link": "",
            "icon": "",
            "icon_size": 18
          }
        },
        "template--16875088249132__900b0644-ef3b-4434-a2e4-746f1dada1bb-16680282293c3ed090-2": {
          "type": "column",
          "settings": {
            "image": "shopify:\/\/shop_images\/ie-banner-16.jpg",
            "title": "QUALITY",
            "title_size": "h4",
            "title_style": "default",
            "text": "<p>Infinite Elements crystal settings come to life through ou proprietary techniques such as Pointiage, which lend an ultra-precise quality to work done by hand. Our attention to detail ensures that each and every piece will always be made of the highest quality. This expertise is infused in every step of the creative process, from initial design sketches through assembly.<\/p>",
            "link_label": "",
            "link": "",
            "icon": "",
            "icon_size": 18
          }
        }
      },
      "block_order": [
        "template--16875088249132__900b0644-ef3b-4434-a2e4-746f1dada1bb-16680282293c3ed090-0",
        "template--16875088249132__900b0644-ef3b-4434-a2e4-746f1dada1bb-16680282293c3ed090-1",
        "template--16875088249132__900b0644-ef3b-4434-a2e4-746f1dada1bb-16680282293c3ed090-2"
      ],
      "settings": {
        "title": "",
        "heading_size": "h1",
        "image_width": "full",
        "image_ratio": "portrait",
        "no_padding_column": true,
        "columns_desktop": 3,
        "column_alignment": "left",
        "background_style": "none",
        "button_label": "",
        "button_link": "",
        "color_scheme": "background-1",
        "columns_mobile": "1",
        "swipe_on_mobile": true,
        "padding_top": 0,
        "padding_bottom": 36
      }
    },
    "527247b3-61f0-4483-bb0f-39f81121c789": {
      "type": "rich-text-2",
      "blocks": {
        "template--16875088249132__527247b3-61f0-4483-bb0f-39f81121c789-16680288369ebc0857-0": {
          "type": "heading",
          "settings": {
            "heading": "<p>Philanthropy<\/p>",
            "heading_size": "h1",
            "heading_style": "2"
          }
        },
        "template--16875088249132__527247b3-61f0-4483-bb0f-39f81121c789-16680288369ebc0857-1": {
          "type": "text",
          "settings": {
            "text": "<p>Since the company was founded, five generations of the Infinite Elements family have upheld a commitment to philanthropy and charitable giving. Caring for people and the planet, qualify, craftmanship and creavity remains at the heart of our values, and today we build on this heritage through our philanthropic programs. <\/p>"
          }
        }
      },
      "block_order": [
        "template--16875088249132__527247b3-61f0-4483-bb0f-39f81121c789-16680288369ebc0857-0",
        "template--16875088249132__527247b3-61f0-4483-bb0f-39f81121c789-16680288369ebc0857-1"
      ],
      "settings": {
        "desktop_content_position": "center",
        "content_alignment": "center",
        "color_scheme": "background-1",
        "full_width": true,
        "padding_top": 80,
        "padding_bottom": 80
      }
    },
    "9e159d9f-5063-4588-b713-ae4cb5a782fd": {
      "type": "multicolumn-2",
      "blocks": {
        "template--16875088249132__9e159d9f-5063-4588-b713-ae4cb5a782fd-1668028864d3ba0722-0": {
          "type": "column",
          "settings": {
            "image": "shopify:\/\/shop_images\/ie-banner-17.jpg",
            "title": "INFINITE ELEMENTS WATERSCHOOL",
            "title_size": "h4",
            "title_style": "default",
            "text": "<p>The Infinite Elements is our flagship communityinvestment program, set up in 2000 to help empower young people across the world to protect our most precious resource and become leaders in sustainable development.<\/p>",
            "link_label": "",
            "link": "",
            "icon": "",
            "icon_size": 18
          }
        },
        "template--16875088249132__9e159d9f-5063-4588-b713-ae4cb5a782fd-1668028864d3ba0722-1": {
          "type": "column",
          "settings": {
            "image": "shopify:\/\/shop_images\/ie-banner-18.jpg",
            "title": "INFINITE ELEMENTS FOUNDATION",
            "title_size": "h4",
            "title_style": "default",
            "text": "<p>The Infinite Elements Foundation was established in 2013 to support charitable initiatives and organizations working in three areas: forstering culture and creavity, promoting human empowerment and preserving the environment.<\/p>",
            "link_label": "",
            "link": "",
            "icon": "",
            "icon_size": 18
          }
        }
      },
      "block_order": [
        "template--16875088249132__9e159d9f-5063-4588-b713-ae4cb5a782fd-1668028864d3ba0722-0",
        "template--16875088249132__9e159d9f-5063-4588-b713-ae4cb5a782fd-1668028864d3ba0722-1"
      ],
      "settings": {
        "title": "",
        "heading_size": "h1",
        "image_width": "full",
        "image_ratio": "adapt",
        "no_padding_column": true,
        "columns_desktop": 2,
        "column_alignment": "center",
        "background_style": "primary",
        "button_label": "",
        "button_link": "",
        "color_scheme": "background-1",
        "columns_mobile": "1",
        "swipe_on_mobile": false,
        "padding_top": 0,
        "padding_bottom": 60
      }
    }
  },
  "order": [
    "6dffa976-689c-49d8-b996-0a573041ba4c",
    "39e64e18-3f0e-4873-8098-f5fd22dcb8f0",
    "656efc8c-cfb3-402b-9bbf-b34e30b9c339",
    "81eb2a91-1801-4318-be24-c82ece53ce1f",
    "2cbf3fba-0910-4e30-962e-98412206bb40",
    "9da261a0-b1c5-4353-be50-dbd2ab52b02b",
    "900b0644-ef3b-4434-a2e4-746f1dada1bb",
    "527247b3-61f0-4483-bb0f-39f81121c789",
    "9e159d9f-5063-4588-b713-ae4cb5a782fd"
  ]
}